./.dockerignore
./.env.example
./.gitignore
./Dockerfile
./LICENSE
./PKG-INFO
./README.md
./env.example
./language.json
./main.py
./main_stdio.py
./package_name
./push_info.json
./pyproject.toml
./readwise_client.py
./render.yaml
./requirements.txt
./test_all_tools.py
./test_mcp_tools.py
./test_server.sh
iflow_mcp_mayankbohra_remote_readwise_mcp-1.0.0.dist-info/METADATA
iflow_mcp_mayankbohra_remote_readwise_mcp-1.0.0.dist-info/WHEEL
iflow_mcp_mayankbohra_remote_readwise_mcp-1.0.0.dist-info/entry_points.txt
iflow_mcp_mayankbohra_remote_readwise_mcp-1.0.0.dist-info/licenses/LICENSE
iflow_mcp_mayankbohra_remote_readwise_mcp-1.0.0.dist-info/RECORD
