Metadata-Version: 2.4
Name: iflow-mcp_mayankbohra-remote-readwise-mcp
Version: 1.0.0
Summary: Readwise MCP Server - Connect your Readwise account to Claude AI
License-File: LICENSE
Requires-Python: >=3.10
Requires-Dist: fastmcp>=2.0.0
Requires-Dist: httpx>=0.27.0
Requires-Dist: pydantic>=2.0.0
Requires-Dist: python-dotenv>=1.0.0
Requires-Dist: starlette>=0.27.0
Requires-Dist: uvicorn>=0.27.0
